{"results": [{"team_name": "ipiudlc", "rankNum": 1, "score": 0.6729489265927978}, {"team_name": "天幕之眼", "rankNum": 2, "score": 0.6724357686980609}, {"team_name": "张十六", "rankNum": 3, "score": 0.6708041897506926}, {"team_name": "uzi", "rankNum": 4, "score": 0.6666184210526316}, {"team_name": "杨门虎将小分队", "rankNum": 5, "score": 0.6655225069252078}, {"team_name": "cccc", "rankNum": 6, "score": 0.6633067867036011}, {"team_name": "iecas_tracking", "rankNum": 7, "score": 0.6480135041551247}, {"team_name": "特没谱", "rankNum": 8, "score": 0.6435841412742382}, {"team_name": "Fighting-sky", "rankNum": 9, "score": 0.6393556959833795}, {"team_name": "CEES_T", "rankNum": 10, "score": 0.637016533933518}, {"team_name": "中南反恐精英", "rankNum": 11, "score": 0.6280269217451524}, {"team_name": "敦品励学 才德并懋", "rankNum": 12, "score": 0.6256739092797783}, {"team_name": "鹰眼三号", "rankNum": 13, "score": 0.6206114958448754}, {"team_name": "天眼察LRF", "rankNum": 14, "score": 0.618299515235457}, {"team_name": "Hust_track_1102", "rankNum": 15, "score": 0.6106603185595568}, {"team_name": "十四所遥感之星", "rankNum": 16, "score": 0.5755711565096953}, {"team_name": "AlphaTang", "rankNum": 17, "score": 0.5700490824099723}, {"team_name": "nbbbbbbbbbb", "rankNum": 18, "score": 0.5650869113573407}, {"team_name": "1907lab", "rankNum": 19, "score": 0.5592054189750693}, {"team_name": "IIPLab", "rankNum": 20, "score": 0.5532044667590028}, {"team_name": "这谁顶的住啊", "rankNum": 21, "score": 0.5508277354570636}, {"team_name": "IMSG", "rankNum": 22, "score": 0.5479611322714683}, {"team_name": "开拓者", "rankNum": 23, "score": 0.5461670706371191}, {"team_name": "训练时长两年半", "rankNum": 24, "score": 0.5452590027700832}, {"team_name": "428->433->329", "rankNum": 25, "score": 0.5401445637119113}, {"team_name": "SZU_COMMODORE", "rankNum": 26, "score": 0.5393801939058172}, {"team_name": "AK04", "rankNum": 27, "score": 0.5390825831024931}, {"team_name": "linlin", "rankNum": 28, "score": 0.5388831371191136}, {"team_name": "focus", "rankNum": 29, "score": 0.5330269217451524}, {"team_name": "TracKING", "rankNum": 30, "score": 0.5318036703601108}, {"team_name": "516", "rankNum": 31, "score": 0.5317659279778394}, {"team_name": "fusionFake", "rankNum": 32, "score": 0.5300980782548477}, {"team_name": "rA9", "rankNum": 33, "score": 0.5300913261772853}, {"team_name": "_SGIIT", "rankNum": 33, "score": 0.5300913261772853}, {"team_name": "Senorita", "rankNum": 35, "score": 0.5275449272853185}, {"team_name": "复仇者联盟", "rankNum": 36, "score": 0.525709487534626}, {"team_name": "一起加油鸭", "rankNum": 37, "score": 0.5214773199445983}, {"team_name": "一江春水向东流", "rankNum": 38, "score": 0.5030664819944599}, {"team_name": "Lover", "rankNum": 39, "score": 0.4911295879501385}, {"team_name": "大头队", "rankNum": 40, "score": 0.48204007963988915}, {"team_name": "天智星云", "rankNum": 41, "score": 0.46853246191135733}, {"team_name": "AIF-AISEEKER", "rankNum": 42, "score": 0.46278601108033246}, {"team_name": "口香糖", "rankNum": 43, "score": 0.46019208795013855}, {"team_name": "小硕永不秃头", "rankNum": 44, "score": 0.42571805747922437}, {"team_name": "SIGMA_OT", "rankNum": 45, "score": 0.38378765581717444}, {"team_name": "研一学习者", "rankNum": 46, "score": 0.26094425207756233}, {"team_name": "lab-612-1", "rankNum": 47, "score": 0.12575302977839337}, {"team_name": "迹", "rankNum": 48, "score": 0.123790425900277}, {"team_name": "CUSTMVRLab", "rankNum": 49, "score": 0.12324437326869807}, {"team_name": "ATP", "rankNum": 50, "score": 0.11471892313019391}]}